[{"location":638,"name":"?C_START","goodness":"SymWithoutRef","description":null},{"location":1321,"name":"?C?CSTPTR","goodness":"GoodSym","description":"char (8-bit) store to general pointer"},{"location":1339,"name":"?C?CSTOPTR","goodness":"GoodSym","description":"char (8-bit) store to general pointer with offset"},{"location":1373,"name":"?C?IILDX","goodness":"GoodSym","description":null},{"location":1395,"name":"?C?ILDPTR","goodness":"GoodSym","description":"int (16-bit) load from general pointer"},{"location":1438,"name":"?C?ILDOPTR","goodness":"GoodSym","description":"int (16-bit) load from general pointer with offset"},{"location":1494,"name":"?C?ISTPTR","goodness":"GoodSym","description":"int (16-bit) store to general pointer"},{"location":1525,"name":"?C?ISTOPTR","goodness":"GoodSym","description":"int (16-bit) store to general pointer with offset"},{"location":1570,"name":"?C?LILDPTR","goodness":"SymWithoutRef","description":"long (32-bit) pre-increment load from general pointer"},{"location":1570,"name":"?C?LLDIPTR","goodness":"SymWithoutRef","description":null},{"location":1570,"name":"?C?LLDPTR","goodness":"SymWithoutRef","description":"long (32-bit) load from general pointer"},{"location":1570,"name":"?C?LLDPTR0","goodness":"SymWithoutRef","description":"long (32-bit) load from general pointer into r3-r0"},{"location":1570,"name":"?C?PLDPTR","goodness":"SymWithoutRef","description":"general pointer load from general pointer"},{"location":1602,"name":"?C?OFFXADD","goodness":"GoodSym","description":null},{"location":1614,"name":"?C?PLDXDATA","goodness":"GoodSym","description":"general pointer load from xdata"},{"location":1623,"name":"?C?PLDIXDATA","goodness":"GoodSym","description":null},{"location":1646,"name":"?C?PSTXDATA","goodness":"GoodSym","description":"general pointer store to xdata"},{"location":1655,"name":"?C?CCASE","goodness":"GoodSym","description":null},{"location":1693,"name":"?C?ICASE","goodness":"GoodSym","description":null},{"location":2164,"name":"?C?LLDIDATA","goodness":"GoodSym","description":"long (32-bit) load from idata (indirect ram access)"},{"location":2176,"name":"?C?LLDXDATA","goodness":"GoodSym","description":"long (32-bit) load from xdata"},{"location":2188,"name":"?C?LLDPDATA","goodness":"GoodSym","description":"long (32-bit) load from pdata (external ram)"},{"location":2200,"name":"?C?LLDCODE","goodness":"GoodSym","description":"long (32-bit) load from code space"},{"location":18516,"name":"?C?LLDIDATA","goodness":"RefOnly","description":"long (32-bit) load from idata (indirect ram access)"},{"location":18516,"name":"?C?LILDIDATA","goodness":"RefOnly","description":"long (32-bit) pre-increment load from idata (indirect ram access)"},{"location":18516,"name":"?C?LLDIIDATA","goodness":"RefOnly","description":null},{"location":18516,"name":"?C?LLDIDATA0","goodness":"RefOnly","description":"long (32-bit) load from idata (indirect ram access) into r3-r0"},{"location":18516,"name":"?C?PLDIDATA","goodness":"RefOnly","description":"general pointer load from idata (indirect ram access)"},{"location":18528,"name":"?C?LLDXDATA","goodness":"RefOnly","description":"long (32-bit) load from xdata"},{"location":18528,"name":"?C?LILDXDATA","goodness":"RefOnly","description":"long (32-bit) pre-increment load from xdata"},{"location":18528,"name":"?C?LLDIXDATA","goodness":"RefOnly","description":null},{"location":18528,"name":"?C?LLDXDATA0","goodness":"RefOnly","description":"long (32-bit) load from xdata into r3-r0"},{"location":18528,"name":"?C?PLDXDATA","goodness":"RefOnly","description":"general pointer load from xdata"},{"location":18540,"name":"?C?LLDPDATA","goodness":"RefOnly","description":"long (32-bit) load from pdata (external ram)"},{"location":18540,"name":"?C?LILDPDATA","goodness":"RefOnly","description":"long (32-bit) pre-increment load from pdata (external ram)"},{"location":18540,"name":"?C?LLDIPDATA","goodness":"RefOnly","description":null},{"location":18540,"name":"?C?LLDPDATA0","goodness":"RefOnly","description":"long (32-bit) load from pdata (external ram) into r3-r0"},{"location":18540,"name":"?C?PLDPDATA","goodness":"RefOnly","description":"general pointer load from pdata (external ram)"},{"location":18552,"name":"?C?LLDCODE","goodness":"RefOnly","description":"long (32-bit) load from code space"},{"location":18552,"name":"?C?LLDCODE0","goodness":"RefOnly","description":"long (32-bit) load from code space into r3-r0"},{"location":18552,"name":"?C?PLDCODE","goodness":"RefOnly","description":"general pointer load from code space"},{"location":22567,"name":"MAIN","goodness":"RefOnly","description":null}]
